{"5":"Gamersgate",
"7":"Gamesplanet fr",
"9":"Cdkeys.com",
"3":"Origin",
"47":"Kinguin",
"40":"Mmoga",
"38":"G2play",
"76":"Gamekeys4u",
"15":"Online-gold",
"66":"Amazon.us",
"63":"Greenmangaming",
"62":"Gamesrocket com",
"77":"Gamersoutlet",
"17":"Gamesdeal",
"8":"Dlgamer.fr",
"64":"Code4game",
"67":"Cjs",
"13":"Instant gaming",
"16":"Gameholds",
"36":"Unlimited_gamestore",
"82":"Gamingpanda",
"31":"Gamekeys4all",
"72":"Gk4me",
"51":"Acheterclecd",
"68":"Amazon.de",
"93":"Game-mart",
"160":"Gameladen",
"69":"Amazon.fr",
"12":"2game",
"73":"Gamingdragons",
"720":"Consoleros",
"477":"Kinguin_marketplace",
"34":"Allcdkey",
"39":"Cdkeyhouse",
"18":"Randyrun",
"611":"G2a_weeklysale",
"721":"Imbakeys",
"96":"Cdkey_express",
"85":"Gameliebe",
"6161":"G2a_marketplace",
"633":"Greenmangaming_633",
"123":"Urcdkeys",
"700":"Gamesplanet de",
"701":"Gamesplanet uk",
"4":"Dlgamer.de",
"310":"Gamesload",
"22":"Dlgamer.es",
"2":"Dlgamer.eu",
"101":"Gamesrocket uk",
"157":"Epicgames",
"109":"Playhappyclub",
"61":"G2a",
"331":"Go4play",
"490":"Play-asia490",
"6":"Orange",
"250":"Nintendo",
"49":"Playasia",
"690":"Amazonfr690",
"911":"Zavvi",
"907":"Ruedecommerce",
"20":"Gog",
"150":"Consogame",
"151":"Ock",
"272":"Eneba",
"122":"Scdkey",
"30":"Cdkeyshere",
"132":"Savemidownload",
"130":"Actihunt",
"131":"Days2play",
"139":"Funstock",
"200":"Dlgamer.us",
"133":"Twed",
"137":"Gamersvalhalla",
"136":"Buygames",
"444":"Battlenet",
"1":"Steam",
"502":"Ubisoft_nl",
"94":"Hrk",
"124":"Imperialgames",
"501":"Gamersgateuk",
"153":"Savemius",
"152":"Savemiuk",
"27":"Less4games",
"81":"Gamebillet",
"216":"Mlgkeys",
"155":"Press_start",
"212":"2game_uk",
"218":"Gamivo",
"213":"2game_us",
"219":"Play_start",
"222":"Voidu",
"26":"Mcgame",
"226":"Dreamgame",
"221":"Nokeys",
"125":"Microsoft",
"156":"Gamesrepublic",
"171":"Goodoffer24",
"260":"Mcgame_de",
"228":"Fanatical",
"503":"Ubisoft_fr",
"303":"Titancodes",
"504":"Ubisoft_uk",
"1252":"Microsoft_de",
"1254":"Microsoft_it",
"301":"Igvault",
"230":"Playstation",
"271":"Micromania",
"162":"Gvgmall",
"688":"Amazonde_marketplace",
"699":"Amazonfr_marketplace",
"231":"Playstation_uk",
"232":"Playstation_de",
"233":"Playstation_it",
"234":"Playstation_es",
"2222":"Voidu_uk",
"919":"Cdkeysdeals",
"172":"Discord",
"173":"Discord_nitro",
"474":"Kinguincr",
"158":"Electronicfirst",
"2720":"Eneba_secondary",
"704":"Gamesplanetus",
"306":"Daxter",
"270":"Allyouplay",
"910":"The_hut",
"315":"Livecards",
"316":"Livekort",
"305":"Aldi",
"317":"Gamerall",
"163":"Software_codes",
"100":"Gamesrocket de",
"149":"Ggcodes",
"308":"Premiumcdkey",
"129":"Difmark",
"307":"Punktid",
"147":"Bzfuture",
"227":"Mtcgame",
"223":"Rockstar",
"174":"Whokeys",
"318":"Livecards_es",
"175":"Bcdkey",
"621":"Gamesrocket_621",
"224":"Vidaplayer",
"273":"Softwareload",
"178":"Battlestategames",
"2700":"Allyouplay_uk",
"176":"Cdkeysales",
"1253":"Microsoft_fr",
"513":"Ubisoft_fr-20",
"512":"Ubisoft_es-20",
"510":"Ubisoft_de-20",
"511":"Ubisoft_nl-20",
"506":"Ubisoft_es",
"505":"Ubisoft_de",
"514":"Ubisoft_uk-20",
"515":"Ubisoft_us-20",
"508":"Ubisoft_us",
"999":"Daisycon",
"126":"Humblebundle",
"252":"Nintendo_de",
"253":"Nintendo_it",
"254":"Nintendo_es",
"1251":"Microsoft_us",
"164":"Nuuvem",
"165":"Direct2drive",
"167":"Square_enix",
"766":"Gamestop",
"2180":"Gamivo_smart",
"312":"Gamesload us",
"166":"Wingamestore",
"2180000":"Gamivo_global",
"168":"Macgamestore",
"680":"Amazon_de_680",
"917":"Boulanger",
"333":"Origin333",
"620":"Gamesrocket_eu620",
"255":"Nintendo_us",
"235":"Playstation_us",
"127":"Indiegala",
"2223":"Voidu_2223",
"2180001":"Wingamestore_global"}